simplifai/.env.vectoredb
simplifai/config.py
simplifai/constants.py
simplifai/db.py
simplifai/helpers.py
simplifai/readers.py
simplifai/rwlock.py
simplifai/vectordb.py
simplifai/wrappers.py
simplifai-0.0.1.dist-info/METADATA
simplifai-0.0.1.dist-info/WHEEL
simplifai-0.0.1.dist-info/licenses/LICENSE
simplifai-0.0.1.dist-info/RECORD
